MANIFEST.in
README.rst
requirements.txt
setup.py
alarme/__init__.py
alarme.egg-info/PKG-INFO
alarme.egg-info/SOURCES.txt
alarme.egg-info/dependency_links.txt
alarme.egg-info/entry_points.txt
alarme.egg-info/requires.txt
alarme.egg-info/top_level.txt
alarme/core/__init__.py
alarme/core/action.py
alarme/core/action_descriptor.py
alarme/core/application.py
alarme/core/essential.py
alarme/core/schedule.py
alarme/core/sensor.py
alarme/core/state.py
alarme/extras/__init__.py
alarme/extras/action/__init__.py
alarme/extras/action/rf_transmitter.py
alarme/extras/action/set_state.py
alarme/extras/action/telegram.py
alarme/extras/action/email/__init__.py
alarme/extras/action/email/email_action.py
alarme/extras/action/email/templates/alarm.html
alarme/extras/action/email/templates/alarm.txt
alarme/extras/action/email/templates/base.html
alarme/extras/action/email/templates/start.html
alarme/extras/action/email/templates/start.txt
alarme/extras/action/gsm/__init__.py
alarme/extras/action/gsm/call_action.py
alarme/extras/action/gsm/gsm_action.py
alarme/extras/action/gsm/sms_action.py
alarme/extras/action/sound/__init__.py
alarme/extras/action/sound/sound_action.py
alarme/extras/common/__init__.py
alarme/extras/common/rf_device.py
alarme/extras/sensor/__init__.py
alarme/extras/sensor/telegram.py
alarme/extras/sensor/rf433/__init__.py
alarme/extras/sensor/rf433/rf_receiver.py
alarme/extras/sensor/web/__init__.py
alarme/extras/sensor/web/filters.py
alarme/extras/sensor/web/util.py
alarme/extras/sensor/web/web_sensor.py
alarme/extras/sensor/web/static/css/bootstrap.min.css
alarme/extras/sensor/web/static/css/style.css
alarme/extras/sensor/web/static/image/logo-icon.png
alarme/extras/sensor/web/static/image/logo.png
alarme/extras/sensor/web/templates/base.html
alarme/extras/sensor/web/templates/control.html
alarme/extras/sensor/web/views/__init__.py
alarme/extras/sensor/web/views/control.py
alarme/extras/sensor/web/views/core.py
alarme/extras/sensor/web/views/home.py
alarme/extras/sensor/web/views/info.py
alarme/overrides/__init__.py
alarme/overrides/logging_extras.py
alarme/scripts/__init__.py
alarme/scripts/common.py
alarme/scripts/server.py