Metadata-Version: 1.0
Name: alarme
Version: 0.6.1
Summary: Universal alarm system
Home-page: https://github.com/insolite/alarme
Author: Oleg Krasnikov
Author-email: a.insolite@gmail.com
License: UNKNOWN
Platform: UNKNOWN
